animethemes_dl/__init__.py
animethemes_dl/__main__.py
animethemes_dl/downloader.py
animethemes_dl/errors.py
animethemes_dl/main.py
animethemes_dl/options.py
animethemes_dl/models/__init__.py
animethemes_dl/models/animethemes.py
animethemes_dl/models/dldata.py
animethemes_dl/models/literals.py
animethemes_dl/models/options.py
animethemes_dl/parsers/__init__.py
animethemes_dl/parsers/__main__.py
animethemes_dl/parsers/anilist.py
animethemes_dl/parsers/animethemes.py
animethemes_dl/parsers/dldata.py
animethemes_dl/parsers/myanimelist.py
animethemes_dl/parsers/parser.py
animethemes_dl/parsers/utils.py
animethemes_dl/tools/__init__.py
animethemes_dl/tools/audio.py
animethemes_dl/tools/colors.py
animethemes_dl/tools/compression.py
animethemes_dl/tools/repair.py
animethemes_dl/tools/tools.py
animethemes_dl-2.1.0.dist-info/LICENSE
animethemes_dl-2.1.0.dist-info/METADATA
animethemes_dl-2.1.0.dist-info/WHEEL
animethemes_dl-2.1.0.dist-info/entry_points.txt
animethemes_dl-2.1.0.dist-info/top_level.txt
animethemes_dl-2.1.0.dist-info/RECORD
