Metadata-Version: 2.1
Name: animethemes-dl
Version: 2.1.0
Summary: Downloads anime themes from animethemes.moe. Supports Batch download and MAL/AniList connecting.
Home-page: https://github.com/thesadru/animethemes-dl
Author: thesadru
Author-email: dan0.suman@gmail.com
License: UNKNOWN
Keywords: mal,anilist,themes,batch,audio,filter,hd,api,ffmpeg,dl,download,animethemes,id3
Platform: UNKNOWN
Classifier: Programming Language :: Python :: 3.8
Classifier: License :: OSI Approved :: MIT License
Classifier: Operating System :: OS Independent
Requires-Python: >=3.8
Requires-Dist: pySmartDl
Requires-Dist: mutagen
Requires-Dist: requests
Requires-Dist: colorama
